README.txt
setup.cfg
setup.py
PylonsGenshi.egg-info/PKG-INFO
PylonsGenshi.egg-info/SOURCES.txt
PylonsGenshi.egg-info/dependency_links.txt
PylonsGenshi.egg-info/entry_points.txt
PylonsGenshi.egg-info/not-zip-safe
PylonsGenshi.egg-info/pkg-info
PylonsGenshi.egg-info/requires.txt
PylonsGenshi.egg-info/top_level.txt
pylonsgenshi/__init__.py
pylonsgenshi/decorators.py
pylonsgenshi/helpers.py
pylonsgenshi/template.py
pylonsgenshi/templating.py
pylonsgenshi/templates/__init__.py
pylonsgenshi/templates/default/MANIFEST.in_tmpl
pylonsgenshi/templates/default/README.txt_tmpl
pylonsgenshi/templates/default/development.ini_tmpl
pylonsgenshi/templates/default/setup.cfg_tmpl
pylonsgenshi/templates/default/setup.py_tmpl
pylonsgenshi/templates/default/test.ini_tmpl
pylonsgenshi/templates/default/+egg+.egg-info/paste_deploy_config.ini_tmpl_tmpl
pylonsgenshi/templates/default/+package+/__init__.py_tmpl
pylonsgenshi/templates/default/+package+/websetup.py_tmpl
pylonsgenshi/templates/default/+package+/config/__init__.py_tmpl
pylonsgenshi/templates/default/+package+/config/environment.py_tmpl
pylonsgenshi/templates/default/+package+/config/middleware.py_tmpl
pylonsgenshi/templates/default/+package+/config/routing.py_tmpl
pylonsgenshi/templates/default/+package+/controllers/__init__.py_tmpl
pylonsgenshi/templates/default/+package+/controllers/error.py_tmpl
pylonsgenshi/templates/default/+package+/controllers/template.py_tmpl
pylonsgenshi/templates/default/+package+/lib/__init__.py_tmpl
pylonsgenshi/templates/default/+package+/lib/app_globals.py_tmpl
pylonsgenshi/templates/default/+package+/lib/base.py_tmpl
pylonsgenshi/templates/default/+package+/lib/helpers.py_tmpl
pylonsgenshi/templates/default/+package+/model/__init__.py_tmpl
pylonsgenshi/templates/default/+package+/public/index.html_tmpl
pylonsgenshi/templates/default/+package+/templates/.distutils_placeholder
pylonsgenshi/templates/default/+package+/tests/__init__.py_tmpl
pylonsgenshi/templates/default/+package+/tests/test_models.py_tmpl
pylonsgenshi/templates/default/+package+/tests/functional/__init__.py_tmpl
pylonsgenshi/templates/default/docs/index.txt_tmpl
pylonsgenshi/templates/default/ez_setup/README.txt
pylonsgenshi/templates/default/ez_setup/__init__.py
