Metadata-Version: 1.0
Name: PylonsGenshi
Version: 0.1.0
Summary: Pylons Project Template Using Genshi As The Templating Language
Home-page: http://pastie.ufsoft.org/wiki/PylonsGenshi
Author: Pedro Algarvio
Author-email: ufs@ufsoft.org
License: BSD
Keywords: web wsgi pylons framework genshi
Platform: UNKNOWN
